{
  "macaulay": [],
  "inaturalist": [
    {
      "filename": "eurasian_tree_sparrow_1.jpg",
      "observation_id": 19417617,
      "photo_id": 29868950,
      "observation_url": "https://www.inaturalist.org/observations/19417617",
      "photographer": "dickypa",
      "license": "all-rights-reserved",
      "credit_format": "\u00a9 dickypa (via iNaturalist), All Rights Reserved"
    },
    {
      "filename": "eurasian_tree_sparrow_2.jpg",
      "observation_id": 1535882,
      "photo_id": 1903005,
      "observation_url": "https://www.inaturalist.org/observations/1535882",
      "photographer": "joyful-islander",
      "license": "cc-by-nc",
      "credit_format": "\u00a9 joyful-islander (via iNaturalist), some rights reserved (CC-BY-NC)"
    },
    {
      "filename": "eurasian_tree_sparrow_3.jpg",
      "observation_id": 199347217,
      "photo_id": 351543905,
      "observation_url": "https://www.inaturalist.org/observations/199347217",
      "photographer": "lisa18716",
      "license": "all-rights-reserved",
      "credit_format": "\u00a9 lisa18716 (via iNaturalist), All Rights Reserved"
    }
  ],
  "wikimedia": [],
  "avibase": []
}