{
  "bird_info": {
    "slug": "red_tailed_laughingthrush",
    "chinese_name": "红尾噪鹛",
    "english_name": "Red-tailed Laughingthrush",
    "scientific_name": "Trochalopteron milnei"
  },
  "macaulay": [
    {
      "original_file": "red_tailed_laughingthrush_538535361.jpg",
      "url": "https://res.cloudinary.com/dzor6lhz8/image/upload/v1768806481/bird-gallery/red_tailed_laughingthrush/macaulay/red_tailed_laughingthrush_538535361.jpg",
      "public_id": "bird-gallery/red_tailed_laughingthrush/macaulay/red_tailed_laughingthrush_538535361",
      "width": 1200,
      "height": 800,
      "format": "jpg",
      "bytes": 101694,
      "attribution": {
        "photographer": "Vincent Wang",
        "photographer_url": "https://macaulaylibrary.org/asset/538535361",
        "license": "© Cornell Lab of Ornithology (non-commercial use)",
        "license_url": "https://support.ebird.org/en/support/solutions/articles/48001064570",
        "credit_format": "Bird by Vincent Wang; Cornell Lab of Ornithology | Macaulay Library",
        "source": "macaulay",
        "source_id": "538535361",
        "note": null
      }
    },
    {
      "original_file": "red_tailed_laughingthrush_627693547.jpg",
      "url": "https://res.cloudinary.com/dzor6lhz8/image/upload/v1768806483/bird-gallery/red_tailed_laughingthrush/macaulay/red_tailed_laughingthrush_627693547.jpg",
      "public_id": "bird-gallery/red_tailed_laughingthrush/macaulay/red_tailed_laughingthrush_627693547",
      "width": 1200,
      "height": 800,
      "format": "jpg",
      "bytes": 112127,
      "attribution": {
        "photographer": "Ben Lucking",
        "photographer_url": "https://macaulaylibrary.org/asset/627693547",
        "license": "© Cornell Lab of Ornithology (non-commercial use)",
        "license_url": "https://support.ebird.org/en/support/solutions/articles/48001064570",
        "credit_format": "Bird by Ben Lucking; Cornell Lab of Ornithology | Macaulay Library",
        "source": "macaulay",
        "source_id": "627693547",
        "note": null
      }
    },
    {
      "original_file": "red_tailed_laughingthrush_638334992.jpg",
      "url": "https://res.cloudinary.com/dzor6lhz8/image/upload/v1768806484/bird-gallery/red_tailed_laughingthrush/macaulay/red_tailed_laughingthrush_638334992.jpg",
      "public_id": "bird-gallery/red_tailed_laughingthrush/macaulay/red_tailed_laughingthrush_638334992",
      "width": 1200,
      "height": 800,
      "format": "jpg",
      "bytes": 100311,
      "attribution": {
        "photographer": "Dorian Anderson",
        "photographer_url": "https://macaulaylibrary.org/asset/638334992",
        "license": "© Cornell Lab of Ornithology (non-commercial use)",
        "license_url": "https://support.ebird.org/en/support/solutions/articles/48001064570",
        "credit_format": "Bird by Dorian Anderson; Cornell Lab of Ornithology | Macaulay Library",
        "source": "macaulay",
        "source_id": "638334992",
        "note": null
      }
    }
  ],
  "inaturalist": [
    {
      "original_file": "red_tailed_laughingthrush_1.jpg",
      "url": "https://res.cloudinary.com/dzor6lhz8/image/upload/v1768806486/bird-gallery/red_tailed_laughingthrush/inaturalist/red_tailed_laughingthrush_1.jpg",
      "public_id": "bird-gallery/red_tailed_laughingthrush/inaturalist/red_tailed_laughingthrush_1",
      "width": 1024,
      "height": 678,
      "format": "jpg",
      "bytes": 69499,
      "attribution": {
        "photographer": "jishenwang",
        "photographer_url": "https://www.inaturalist.org/observations/32634061",
        "license": "all-rights-reserved",
        "license_url": null,
        "credit_format": "© jishenwang (via iNaturalist), All Rights Reserved",
        "source": "inaturalist",
        "source_id": 32634061,
        "note": null
      }
    },
    {
      "original_file": "red_tailed_laughingthrush_2.jpg",
      "url": "https://res.cloudinary.com/dzor6lhz8/image/upload/v1768806486/bird-gallery/red_tailed_laughingthrush/inaturalist/red_tailed_laughingthrush_2.jpg",
      "public_id": "bird-gallery/red_tailed_laughingthrush/inaturalist/red_tailed_laughingthrush_2",
      "width": 1024,
      "height": 683,
      "format": "jpg",
      "bytes": 60926,
      "attribution": {
        "photographer": "theweenuthatch",
        "photographer_url": "https://www.inaturalist.org/observations/266753758",
        "license": "cc-by",
        "license_url": null,
        "credit_format": "© theweenuthatch (via iNaturalist), some rights reserved (CC-BY)",
        "source": "inaturalist",
        "source_id": 266753758,
        "note": null
      }
    },
    {
      "original_file": "red_tailed_laughingthrush_3.jpg",
      "url": "https://res.cloudinary.com/dzor6lhz8/image/upload/v1768806488/bird-gallery/red_tailed_laughingthrush/inaturalist/red_tailed_laughingthrush_3.jpg",
      "public_id": "bird-gallery/red_tailed_laughingthrush/inaturalist/red_tailed_laughingthrush_3",
      "width": 1024,
      "height": 768,
      "format": "jpg",
      "bytes": 138809,
      "attribution": {
        "photographer": "redpandacat",
        "photographer_url": "https://www.inaturalist.org/observations/39482178",
        "license": "cc-by-nc-sa",
        "license_url": null,
        "credit_format": "© redpandacat (via iNaturalist), some rights reserved (CC-BY-NC-SA)",
        "source": "inaturalist",
        "source_id": 39482178,
        "note": null
      }
    }
  ],
  "birdphotos": [],
  "wikimedia": [
    {
      "original_file": "red_tailed_laughingthrush_1.jpg",
      "url": "https://res.cloudinary.com/dzor6lhz8/image/upload/v1768806489/bird-gallery/red_tailed_laughingthrush/wikimedia/red_tailed_laughingthrush_1.jpg",
      "public_id": "bird-gallery/red_tailed_laughingthrush/wikimedia/red_tailed_laughingthrush_1",
      "width": 1280,
      "height": 853,
      "format": "jpg",
      "bytes": 191333,
      "attribution": {
        "photographer": null,
        "photographer_url": null,
        "license": null,
        "license_url": null,
        "credit_format": null,
        "source": "wikimedia",
        "source_id": null,
        "note": "署名信息待补充"
      }
    }
  ],
  "avibase": [
    {
      "original_file": "avibase_1_52778697576_3b7e0ec5e0_b.jpg",
      "url": "https://res.cloudinary.com/dzor6lhz8/image/upload/v1768806490/bird-gallery/red_tailed_laughingthrush/avibase/avibase_1_52778697576_3b7e0ec5e0_b.jpg",
      "public_id": "bird-gallery/red_tailed_laughingthrush/avibase/avibase_1_52778697576_3b7e0ec5e0_b",
      "width": 1024,
      "height": 683,
      "format": "jpg",
      "bytes": 117426,
      "attribution": {
        "photographer": null,
        "photographer_url": null,
        "license": null,
        "license_url": null,
        "credit_format": null,
        "source": "avibase",
        "source_id": "52778697576",
        "note": "署名信息需从Flickr获取"
      }
    },
    {
      "original_file": "avibase_2_49389437118_b79da0466b_b.jpg",
      "url": "https://res.cloudinary.com/dzor6lhz8/image/upload/v1768806491/bird-gallery/red_tailed_laughingthrush/avibase/avibase_2_49389437118_b79da0466b_b.jpg",
      "public_id": "bird-gallery/red_tailed_laughingthrush/avibase/avibase_2_49389437118_b79da0466b_b",
      "width": 683,
      "height": 1024,
      "format": "jpg",
      "bytes": 119685,
      "attribution": {
        "photographer": null,
        "photographer_url": null,
        "license": null,
        "license_url": null,
        "credit_format": null,
        "source": "avibase",
        "source_id": "49389437118",
        "note": "署名信息需从Flickr获取"
      }
    },
    {
      "original_file": "avibase_3_52778953194_7b0e803512_b.jpg",
      "url": "https://res.cloudinary.com/dzor6lhz8/image/upload/v1768806492/bird-gallery/red_tailed_laughingthrush/avibase/avibase_3_52778953194_7b0e803512_b.jpg",
      "public_id": "bird-gallery/red_tailed_laughingthrush/avibase/avibase_3_52778953194_7b0e803512_b",
      "width": 1024,
      "height": 683,
      "format": "jpg",
      "bytes": 93345,
      "attribution": {
        "photographer": null,
        "photographer_url": null,
        "license": null,
        "license_url": null,
        "credit_format": null,
        "source": "avibase",
        "source_id": "52778953194",
        "note": "署名信息需从Flickr获取"
      }
    }
  ],
  "sounds": [
    {
      "original_file": "red_tailed_laughingthrush_203899031.mp3",
      "url": "https://res.cloudinary.com/dzor6lhz8/video/upload/v1768806560/bird-gallery/red_tailed_laughingthrush/sounds/red_tailed_laughingthrush_203899031.mp3",
      "public_id": "bird-gallery/red_tailed_laughingthrush/sounds/red_tailed_laughingthrush_203899031",
      "duration": 28.848,
      "format": "mp3",
      "bytes": 670364,
      "bit_rate": 185902,
      "audio_codec": "mp3",
      "audio_frequency": 48000,
      "attribution": {
        "recordist": "Unknown",
        "source": "macaulay",
        "source_id": "203899031",
        "asset_url": "https://macaulaylibrary.org/asset/203899031",
        "license": "© Cornell Lab of Ornithology (non-commercial use)",
        "license_url": "https://support.ebird.org/en/support/solutions/articles/48001064570",
        "note": null
      }
    }
  ]
}